marmite-0.2.7.data/scripts/marmite
marmite-0.2.7.dist-info/METADATA
marmite-0.2.7.dist-info/WHEEL
marmite-0.2.7.dist-info/licenses/LICENSE
python/marmite/__init__.py
python/marmite/__main__.py
python/marmite/py.typed
marmite-0.2.7.dist-info/RECORD
