Metadata-Version: 2.4
Name: marmite
Version: 0.2.7
Classifier: Development Status :: 4 - Beta
Classifier: Environment :: Console
Classifier: Intended Audience :: Developers
Classifier: Intended Audience :: End Users/Desktop
Classifier: License :: OSI Approved :: GNU Affero General Public License v3 or later (AGPLv3+)
Classifier: Operating System :: OS Independent
Classifier: Programming Language :: Python :: 3
Classifier: Programming Language :: Python :: 3.8
Classifier: Programming Language :: Python :: 3.9
Classifier: Programming Language :: Python :: 3.10
Classifier: Programming Language :: Python :: 3.11
Classifier: Programming Language :: Python :: 3.12
Classifier: Programming Language :: Rust
Classifier: Topic :: Internet :: WWW/HTTP :: Site Management
Classifier: Topic :: Software Development :: Build Tools
Classifier: Topic :: Text Processing :: Markup :: HTML
Classifier: Topic :: Text Processing :: Markup :: Markdown
License-File: LICENSE
Summary: Marmite is the easiest static site generator.
Keywords: web,blog,static,site,html,generator,markdown
Home-Page: https://marmite.blog
Author-email: Bruno Rocha <rochacbruno@gmail.com>
License: AGPL-3.0-or-later
Requires-Python: >=3.8
Project-URL: Homepage, https://marmite.blog
Project-URL: Documentation, https://marmite.blog
Project-URL: Repository, https://github.com/rochacbruno/marmite
Project-URL: Bug Tracker, https://github.com/rochacbruno/marmite/issues
